.gitignore
CHANGES.txt
COPYRIGHT.txt
LICENSE.txt
README.rst
coverage.sh
setup.py
test
docs/Makefile
docs/api.rst
docs/conf.py
docs/index.rst
docs/.static/koansys.css
docs/.static/koansyslogo.png
udr/__init__.py
udr/tests.py
udr.egg-info/PKG-INFO
udr.egg-info/SOURCES.txt
udr.egg-info/dependency_links.txt
udr.egg-info/not-zip-safe
udr.egg-info/top_level.txt