Metadata-Version: 1.0
Name: udr
Version: 1.0
Summary: A Unicode Dict Reader for CSV files
Home-page: http://koansys.org
Author: Koansys, LLC
Author-email: info@koansys.org
License: BSD-derived (http://koansys.org/LICENSE.txt)
Keywords: csv
Platform: UNKNOWN
Classifier: Intended Audience :: Developers
Classifier: Programming Language :: Python
